{
  "id": "components/dyte-file-message",
  "title": "DyteFileMessage",
  "description": "Learn how to use and customize the DyteFileMessage component in Dyte's React Native UI Kit with our detailed documentation.",
  "source": "@site/docs/rn-ui-kit/components/dyte-file-message.mdx",
  "sourceDirName": "components",
  "slug": "/components/dyte-file-message",
  "permalink": "/react-native/components/dyte-file-message",
  "draft": false,
  "unlisted": false,
  "editUrl": "https://github.com/dyte-io/docs/tree/main/docs/rn-ui-kit/components/dyte-file-message.mdx",
  "tags": [],
  "version": "current",
  "lastUpdatedAt": 1539502055,
  "formattedLastUpdatedAt": "Oct 14, 2018",
  "frontMatter": {
    "description": "Learn how to use and customize the DyteFileMessage component in Dyte's React Native UI Kit with our detailed documentation."
  },
  "sidebar": "tutorialSidebar",
  "previous": {
    "title": "DyteEndedScreen",
    "permalink": "/react-native/components/dyte-ended-screen"
  },
  "next": {
    "title": "DyteGridPagination",
    "permalink": "/react-native/components/dyte-grid-pagination"
  }
}