{
  "label": "ios-core",
  "permalink": "/ios-core/tags/ios-core",
  "allTagsPath": "/ios-core/tags",
  "count": 2,
  "items": [
    {
      "id": "room/room-connection-events",
      "title": "Room Connection Events",
      "description": "Explore room connection events in iOS Core with Dyte Docs. Understand how to leverage these events for enhanced user experiences.",
      "permalink": "/ios-core/room/room-connection-events"
    },
    {
      "id": "local-user/screen-share-guide",
      "title": "Sharing screen on iOS",
      "description": "This document explains how to setup screen sharing on a iOS App using Dyte SDK",
      "permalink": "/ios-core/local-user/screen-share-guide"
    }
  ],
  "unlisted": false
}