{
  "id": "usage/stores-api/manage-stores",
  "title": "Operations on Store",
  "description": "Learn how to manage stores in Dyte's Plugin SDK Usage documentation. Effectively handle and organize stores for seamless plugin development. Dyte Docs.",
  "source": "@site/docs/plugin-sdk/usage/stores-api/manage-stores.mdx",
  "sourceDirName": "usage/stores-api",
  "slug": "/usage/stores-api/manage-stores",
  "permalink": "/plugin-sdk/usage/stores-api/manage-stores",
  "draft": false,
  "unlisted": false,
  "editUrl": "https://github.com/dyte-io/docs/tree/main/docs/plugin-sdk/usage/stores-api/manage-stores.mdx",
  "tags": [],
  "version": "current",
  "lastUpdatedAt": 1539502055000,
  "sidebarPosition": 2,
  "frontMatter": {
    "title": "Operations on Store",
    "sidebar_position": 2,
    "description": "Learn how to manage stores in Dyte's Plugin SDK Usage documentation. Effectively handle and organize stores for seamless plugin development. Dyte Docs."
  },
  "sidebar": "tutorialSidebar",
  "previous": {
    "title": "Introduction",
    "permalink": "/plugin-sdk/usage/stores-api/introduction"
  },
  "next": {
    "title": "How to work with Plugin Stores",
    "permalink": "/plugin-sdk/guides/how-to-work-with-plugin-stores"
  }
}